onipynbrenderer/__init__.py
onipynbrenderer/custom_exception.py
onipynbrenderer/logger.py
onipynbrenderer/site.py
onipynbrenderer/youtube.py
onipynbrenderer-0.0.5.dist-info/LICENSE
onipynbrenderer-0.0.5.dist-info/METADATA
onipynbrenderer-0.0.5.dist-info/WHEEL
onipynbrenderer-0.0.5.dist-info/top_level.txt
onipynbrenderer-0.0.5.dist-info/RECORD
